gwproto/__init__.py
gwproto/data_classes/__init__.py
gwproto/data_classes/components/__init__.py
gwproto/data_classes/components/ads111x_based_component.py
gwproto/data_classes/components/component.py
gwproto/data_classes/components/dfr_component.py
gwproto/data_classes/components/electric_meter_component.py
gwproto/data_classes/components/fibaro_smart_implant_component.py
gwproto/data_classes/components/hubitat_component.py
gwproto/data_classes/components/hubitat_poller_component.py
gwproto/data_classes/components/hubitat_tank_component.py
gwproto/data_classes/components/i2c_multichannel_dt_relay_component.py
gwproto/data_classes/components/pico_btu_meter_component.py
gwproto/data_classes/components/pico_flow_module_component.py
gwproto/data_classes/components/pico_tank_module_component.py
gwproto/data_classes/components/resistive_heater_component.py
gwproto/data_classes/components/rest_poller_component.py
gwproto/data_classes/components/web_server_component.py
gwproto/data_classes/data_channel.py
gwproto/data_classes/hardware_layout.py
gwproto/data_classes/mixin.py
gwproto/data_classes/resolver.py
gwproto/data_classes/sh_node.py
gwproto/data_classes/synth_channel.py
gwproto/data_classes/telemetry_tuple.py
gwproto/decoders.py
gwproto/default_decoders.py
gwproto/enums/__init__.py
gwproto/enums/actor_class.py
gwproto/enums/admin_event.py
gwproto/enums/admin_state.py
gwproto/enums/alert_priority.py
gwproto/enums/aquastat_control.py
gwproto/enums/change_aquastat_control.py
gwproto/enums/change_heat_pump_control.py
gwproto/enums/change_heatcall_source.py
gwproto/enums/change_primary_pump_control.py
gwproto/enums/change_relay_pin.py
gwproto/enums/change_relay_state.py
gwproto/enums/change_store_flow_relay.py
gwproto/enums/change_valve_state.py
gwproto/enums/fsm_action_type.py
gwproto/enums/fsm_name.py
gwproto/enums/fsm_report_type.py
gwproto/enums/gpm_from_hz_method.py
gwproto/enums/heat_pump_control.py
gwproto/enums/heatcall_source.py
gwproto/enums/hz_calc_method.py
gridworks_protocol-1.3.3.dist-info/LICENSE
gridworks_protocol-1.3.3.dist-info/METADATA
gridworks_protocol-1.3.3.dist-info/WHEEL
gridworks_protocol-1.3.3.dist-info/RECORD
