Metadata-Version: 2.1
Name: gridworks-protocol
Version: 1.3.3
Summary: Gridworks Protocol
Home-page: https://github.com/thegridelectric/gridworks-protocol
License: MIT
Author: Jessica Millar
Author-email: jmillar@gridworks-consulting.com
Requires-Python: >=3.11,<4.0
Classifier: Development Status :: 2 - Pre-Alpha
Classifier: License :: OSI Approved :: MIT License
Classifier: Programming Language :: Python :: 3
Classifier: Programming Language :: Python :: 3.11
Classifier: Programming Language :: Python :: 3.12
Requires-Dist: gridworks (>=1.5.6,<2.0.0)
Requires-Dist: pydantic (>=2.8.2,<3.0.0)
Requires-Dist: pydantic-extra-types (>=2.9.0,<3.0.0)
Requires-Dist: pytz (>=2024.1,<2025.0)
Requires-Dist: yarl (>=1.9.2,<2.0.0)
Project-URL: Changelog, https://github.com/thegridelectric/gridworks-protocol/releases
Project-URL: Documentation, https://gridworks-protocol.readthedocs.io
Project-URL: Repository, https://github.com/thegridelectric/gridworks-protocol
